nysg_tools/__init__.py
nysg_tools/main.py
nysg_tools-0.8.dist-info/LICENSE
nysg_tools-0.8.dist-info/METADATA
nysg_tools-0.8.dist-info/WHEEL
nysg_tools-0.8.dist-info/top_level.txt
nysg_tools-0.8.dist-info/RECORD
