Metadata-Version: 2.1
Name: nysg-tools
Version: 0.8
Summary: Una colección de herramientas utiles para los laboratorios de la UBA FCEN
Home-page: https://github.com/Noya-santiago/nysg_tools
Author: Santiago Noya
Author-email: noyasantiagomail@gmail.com
License-File: LICENSE
Requires-Dist: numpy
Requires-Dist: pandas
